SigProfilerTopographyCombiner/__init__.py
SigProfilerTopographyCombiner/version.py
SigProfilerTopographyCombiner/source/Combined_Common.py
SigProfilerTopographyCombiner/source/Combined_Heatmaps_For_DNA_Elements.py
SigProfilerTopographyCombiner/source/Combined_Occupancy_ReplicationTime_Processivity.py
SigProfilerTopographyCombiner/source/Combined_Strand_Bias_Figures.py
SigProfilerTopographyCombiner/source/Topography_Combiner.py
SigProfilerTopographyCombiner-1.0.2.dist-info/METADATA
SigProfilerTopographyCombiner-1.0.2.dist-info/WHEEL
SigProfilerTopographyCombiner-1.0.2.dist-info/top_level.txt
SigProfilerTopographyCombiner-1.0.2.dist-info/RECORD
