Metadata-Version: 2.1
Name: SigProfilerTopographyCombiner
Version: 1.0.2
Summary: SigProfilerTopographyCombiner combines separate SigProfilerTopography runs.
Home-page: https://github.com/AlexandrovLab/SigProfilerTopographyCombiner
Author: Burcak Otlu
Author-email: burcakotlu@eng.ucsd.edu
License: UCSD
Platform: UNKNOWN
Requires-Dist: SigProfilerTopography (>=1.0.68)
Requires-Dist: XlsxWriter (>=1.3.7)
Requires-Dist: pandas (>=1.1.5)
Requires-Dist: numpy (>=1.20.1)
Requires-Dist: matplotlib (>=2.2.2)
Requires-Dist: scipy (>=1.1.0)
Requires-Dist: statsmodels (>=0.9.0)
